{
    "@context": "http://www.shared-canvas.org/ns/context.json",
    "@id": "https://raw.githubusercontent.com/nakamura196/omekac_kunshujo/master/docs/oa/items/7055/annolist.json",
    "@type": "sc:AnnotationList",
    "resources": [
        {
            "@context": "http://iiif.io/api/presentation/2/context.json",
            "@id": "https://diyhistory.org/public/kunshujo/oa/items/42553/anno.json",
            "@type": "oa:Annotation",
            "motivation": [
                "oa:commenting",
                "oa:tagging"
            ],
            "on": [
                {
                    "@type": "oa:SpecificResource",
                    "full": "https://iiif.dl.itc.u-tokyo.ac.jp/repo/iiif/d92bfa51-20c9-4343-931a-e1cee9fffaeb/canvas/p104",
                    "selector": {
                        "@type": "oa:Choice",
                        "default": {
                            "@type": "oa:FragmentSelector",
                            "value": "xywh=1194,1531,2838,3669"
                        },
                        "item": {
                            "@type": "oa:SvgSelector",
                            "value": "<svg xmlns='http://www.w3.org/2000/svg'><path xmlns=\"http://www.w3.org/2000/svg\" d=\"M4031.37679,5200.18831h-1418.91326v0h-1418.91326v-1834.59801v-1834.59801h1418.91326h1418.91326v1834.59801z\" data-paper-data=\"{&quot;strokeWidth&quot;:1,&quot;rotation&quot;:0,&quot;annotation&quot;:null,&quot;nonHoverStrokeColor&quot;:[&quot;Color&quot;,0,0.74902,1],&quot;editable&quot;:true}\" id=\"rectangle_40439846-bae3-4229-abce-8598c1feca13\" fill-opacity=\"0.00001\" fill=\"#00bfff\" fill-rule=\"nonzero\" stroke=\"#00bfff\" stroke-width=\"12.78064\" stroke-linecap=\"butt\" stroke-linejoin=\"miter\" stroke-miterlimit=\"10\" stroke-dasharray=\"\" stroke-dashoffset=\"0\" font-family=\"none\" font-weight=\"none\" font-size=\"none\" text-anchor=\"none\" style=\"mix-blend-mode: normal\"/></svg>"
                        }
                    },
                    "within": {
                        "@id": "https://raw.githubusercontent.com/nakamura196/omekac_kunshujo/master/docs/oa/collections/57/manifest.json",
                        "@type": "sc:Manifest"
                    }
                }
            ],
            "resource": [
                {
                    "@type": "dctypes:Text",
                    "chars": "<p>村上美和、佘欣怡</p>",
                    "format": "text/html"
                },
                {
                    "@type": "oa:Tag",
                    "chars": "Banden"
                },
                {
                    "@type": "oa:Tag",
                    "chars": "伴傳兵衛"
                },
                {
                    "@type": "oa:Tag",
                    "chars": "伴傳支店"
                }
            ]
        },
        {
            "@context": "http://iiif.io/api/presentation/2/context.json",
            "@id": "https://diyhistory.org/public/kunshujo/oa/items/42554/anno.json",
            "@type": "oa:Annotation",
            "motivation": [
                "oa:commenting",
                "oa:tagging"
            ],
            "on": [
                {
                    "@type": "oa:SpecificResource",
                    "full": "https://iiif.dl.itc.u-tokyo.ac.jp/repo/iiif/d92bfa51-20c9-4343-931a-e1cee9fffaeb/canvas/p104",
                    "selector": {
                        "@type": "oa:Choice",
                        "default": {
                            "@type": "oa:FragmentSelector",
                            "value": "xywh=4110,2058,2825,3126"
                        },
                        "item": {
                            "@type": "oa:SvgSelector",
                            "value": "<svg xmlns='http://www.w3.org/2000/svg'><path xmlns=\"http://www.w3.org/2000/svg\" d=\"M4109.78809,5183.63845h1412.68188v0h1412.68188v-1562.96243v-1562.96243h-1412.68188h-1412.68188v1562.96243z\" data-paper-data=\"{&quot;strokeWidth&quot;:1,&quot;rotation&quot;:0,&quot;annotation&quot;:null,&quot;nonHoverStrokeColor&quot;:[&quot;Color&quot;,0,0.74902,1],&quot;editable&quot;:true}\" id=\"rectangle_1a301356-6122-4b70-8e89-7ef55194bc33\" fill-opacity=\"0.00001\" fill=\"#00bfff\" fill-rule=\"nonzero\" stroke=\"#00bfff\" stroke-width=\"27.65112\" stroke-linecap=\"butt\" stroke-linejoin=\"miter\" stroke-miterlimit=\"10\" stroke-dasharray=\"\" stroke-dashoffset=\"0\" font-family=\"none\" font-weight=\"none\" font-size=\"none\" text-anchor=\"none\" style=\"mix-blend-mode: normal\"/></svg>"
                        }
                    },
                    "within": {
                        "@id": "https://diyhistory.org/public/kunshujo/oa/collections/57/manifest.json",
                        "@type": "sc:Manifest"
                    }
                }
            ],
            "resource": [
                {
                    "@type": "dctypes:Text",
                    "chars": "<p>村上美和、佘欣怡</p>",
                    "format": "text/html"
                },
                {
                    "@type": "oa:Tag",
                    "chars": "Jiyute"
                },
                {
                    "@type": "oa:Tag",
                    "chars": "Sandwich"
                },
                {
                    "@type": "oa:Tag",
                    "chars": "サンドウィッチ"
                },
                {
                    "@type": "oa:Tag",
                    "chars": "自由亭支店"
                }
            ]
        },
        {
            "@context": "http://iiif.io/api/presentation/2/context.json",
            "@id": "https://diyhistory.org/public/kunshujo/oa/items/42555/anno.json",
            "@type": "oa:Annotation",
            "motivation": [
                "oa:commenting",
                "oa:tagging"
            ],
            "on": [
                {
                    "@type": "oa:SpecificResource",
                    "full": "https://iiif.dl.itc.u-tokyo.ac.jp/repo/iiif/d92bfa51-20c9-4343-931a-e1cee9fffaeb/canvas/p104",
                    "selector": {
                        "@type": "oa:Choice",
                        "default": {
                            "@type": "oa:FragmentSelector",
                            "value": "xywh=1173,735,3758,755"
                        },
                        "item": {
                            "@type": "oa:SvgSelector",
                            "value": "<svg xmlns='http://www.w3.org/2000/svg'><path xmlns=\"http://www.w3.org/2000/svg\" d=\"M1173.17256,735.36318h1878.97184v0h1878.97184v377.36245v377.36245h-1878.97184h-1878.97184v-377.36245z\" data-paper-data=\"{&quot;strokeWidth&quot;:1,&quot;rotation&quot;:0,&quot;annotation&quot;:null,&quot;nonHoverStrokeColor&quot;:[&quot;Color&quot;,0,0.74902,1],&quot;editable&quot;:true}\" id=\"rectangle_330bd039-c57f-42f6-9351-1e99cf3e581a\" fill-opacity=\"0.00001\" fill=\"#00bfff\" fill-rule=\"nonzero\" stroke=\"#00bfff\" stroke-width=\"2.85347\" stroke-linecap=\"butt\" stroke-linejoin=\"miter\" stroke-miterlimit=\"10\" stroke-dasharray=\"\" stroke-dashoffset=\"0\" font-family=\"none\" font-weight=\"none\" font-size=\"none\" text-anchor=\"none\" style=\"mix-blend-mode: normal\"/></svg>"
                        }
                    },
                    "within": {
                        "@id": "https://diyhistory.org/public/kunshujo/oa/collections/57/manifest.json",
                        "@type": "sc:Manifest"
                    }
                }
            ],
            "resource": [
                {
                    "@type": "dctypes:Text",
                    "chars": "<p>村上美和、佘欣怡</p>",
                    "format": "text/html"
                },
                {
                    "@type": "oa:Tag",
                    "chars": "丹後名産_金太郎_いわし"
                },
                {
                    "@type": "oa:Tag",
                    "chars": "丹後宮津港"
                },
                {
                    "@type": "oa:Tag",
                    "chars": "前田庄助"
                },
                {
                    "@type": "oa:Tag",
                    "chars": "天の橋立"
                },
                {
                    "@type": "oa:Tag",
                    "chars": "鰛"
                }
            ]
        },
        {
            "@context": "http://iiif.io/api/presentation/2/context.json",
            "@id": "https://diyhistory.org/public/kunshujo/oa/items/42556/anno.json",
            "@type": "oa:Annotation",
            "motivation": [
                "oa:commenting",
                "oa:tagging"
            ],
            "on": [
                {
                    "@type": "oa:SpecificResource",
                    "full": "https://iiif.dl.itc.u-tokyo.ac.jp/repo/iiif/d92bfa51-20c9-4343-931a-e1cee9fffaeb/canvas/p104",
                    "selector": {
                        "@type": "oa:Choice",
                        "default": {
                            "@type": "oa:FragmentSelector",
                            "value": "xywh=4923,760,1973,1283"
                        },
                        "item": {
                            "@type": "oa:SvgSelector",
                            "value": "<svg xmlns='http://www.w3.org/2000/svg'><path xmlns=\"http://www.w3.org/2000/svg\" d=\"M4923.34523,2043.20168h986.29633v0h986.29633v-641.66509v-641.66509h-986.29633h-986.29633v641.66509z\" data-paper-data=\"{&quot;strokeWidth&quot;:1,&quot;rotation&quot;:0,&quot;annotation&quot;:null,&quot;nonHoverStrokeColor&quot;:[&quot;Color&quot;,0,0.74902,1],&quot;editable&quot;:true}\" id=\"rectangle_1ef0f431-9ffa-4610-bc27-76b39f245634\" fill-opacity=\"0.00001\" fill=\"#00bfff\" fill-rule=\"nonzero\" stroke=\"#00bfff\" stroke-width=\"15.92704\" stroke-linecap=\"butt\" stroke-linejoin=\"miter\" stroke-miterlimit=\"10\" stroke-dasharray=\"\" stroke-dashoffset=\"0\" font-family=\"none\" font-weight=\"none\" font-size=\"none\" text-anchor=\"none\" style=\"mix-blend-mode: normal\"/></svg>"
                        }
                    },
                    "within": {
                        "@id": "https://diyhistory.org/public/kunshujo/oa/collections/57/manifest.json",
                        "@type": "sc:Manifest"
                    }
                }
            ],
            "resource": [
                {
                    "@type": "dctypes:Text",
                    "chars": "<p>村上美和、佘欣怡</p>",
                    "format": "text/html"
                },
                {
                    "@type": "oa:Tag",
                    "chars": "Senshodo"
                },
                {
                    "@type": "oa:Tag",
                    "chars": "ジョジバント氏英学校"
                },
                {
                    "@type": "oa:Tag",
                    "chars": "内外向_扇子"
                },
                {
                    "@type": "oa:Tag",
                    "chars": "扇勝堂"
                }
            ]
        }
    ]
}