{
    "@context": "http://www.shared-canvas.org/ns/context.json",
    "@id": "https://raw.githubusercontent.com/nakamura196/omekac_kunshujo/master/docs/oa/items/11159/annolist.json",
    "@type": "sc:AnnotationList",
    "resources": [
        {
            "@context": "http://iiif.io/api/presentation/2/context.json",
            "@id": "https://diyhistory.org/public/kunshujo/oa/items/53702/anno.json",
            "@type": "oa:Annotation",
            "motivation": [
                "oa:tagging",
                "oa:commenting"
            ],
            "on": [
                {
                    "@type": "oa:SpecificResource",
                    "full": "https://iiif.dl.itc.u-tokyo.ac.jp/repo/iiif/c9e4d2a8-4e68-4e05-9d06-e371a3246ff0/canvas/p99",
                    "selector": {
                        "@type": "oa:Choice",
                        "default": {
                            "@type": "oa:FragmentSelector",
                            "value": "xywh=3980,656,2993,1976"
                        },
                        "item": {
                            "@type": "oa:SvgSelector",
                            "value": "<svg xmlns='http://www.w3.org/2000/svg'><path xmlns=\"http://www.w3.org/2000/svg\" d=\"M6973.25889,2632.50328h-1496.39556v0h-1496.39556v-988.20795v-988.20795h1496.39556h1496.39556v988.20795z\" data-paper-data=\"{&quot;strokeWidth&quot;:1,&quot;rotation&quot;:0,&quot;deleteIcon&quot;:null,&quot;rotationIcon&quot;:null,&quot;group&quot;:null,&quot;editable&quot;:true,&quot;annotation&quot;:null}\" id=\"rectangle_2d16d979-dcc0-4324-88f7-8b11884e763e\" fill-opacity=\"0\" fill=\"#00bfff\" fill-rule=\"nonzero\" stroke=\"#00bfff\" stroke-width=\"1\" stroke-linecap=\"butt\" stroke-linejoin=\"miter\" stroke-miterlimit=\"10\" stroke-dasharray=\"\" stroke-dashoffset=\"0\" font-family=\"none\" font-weight=\"none\" font-size=\"none\" text-anchor=\"none\" style=\"mix-blend-mode: normal\"/></svg>"
                        }
                    },
                    "within": {
                        "@id": "https://raw.githubusercontent.com/nakamura196/omekac_kunshujo/master/docs/oa/collections/84/manifest.json",
                        "@type": "sc:Manifest"
                    }
                }
            ],
            "resource": [
                {
                    "@type": "dctypes:Text",
                    "chars": "<p>木下優友</p>\n<p>[kun087-098-002]</p>",
                    "format": "text/html"
                },
                {
                    "@type": "oa:Tag",
                    "chars": "ミツワ家庭薬"
                },
                {
                    "@type": "oa:Tag",
                    "chars": "ミツワ石鹸"
                },
                {
                    "@type": "oa:Tag",
                    "chars": "ミツワ香水"
                },
                {
                    "@type": "oa:Tag",
                    "chars": "専売特許第20238号"
                },
                {
                    "@type": "oa:Tag",
                    "chars": "東京＿丸見屋商店"
                },
                {
                    "@type": "oa:Tag",
                    "chars": "肝油ドロップス"
                }
            ]
        }
    ]
}