{
    "@id": "https://diyhistory.org/public/kunshujo/api/42957.json",
    "added": "2021-01-18T06:59:48+00:00",
    "collection": null,
    "element_texts": [
        {
            "element": {
                "id": 102,
                "name": "On Canvas",
                "resource": "elements",
                "url": "https://diyhistory.org/public/kunshujo/api/elements/102"
            },
            "element_set": {
                "id": 3,
                "name": "Item Type Metadata",
                "resource": "element_sets",
                "url": "https://diyhistory.org/public/kunshujo/api/element_sets/3"
            },
            "html": false,
            "text": "5dcddf93-a965-4165-9cc9-1b7dee7a397b"
        },
        {
            "element": {
                "id": 105,
                "name": "UUID",
                "resource": "elements",
                "url": "https://diyhistory.org/public/kunshujo/api/elements/105"
            },
            "element_set": {
                "id": 5,
                "name": "IIIF Item Metadata",
                "resource": "element_sets",
                "url": "https://diyhistory.org/public/kunshujo/api/element_sets/5"
            },
            "html": false,
            "text": "cc4d2281-dbe3-4f12-a181-c42a3f37ff1c"
        },
        {
            "element": {
                "id": 95,
                "name": "Original @id",
                "resource": "elements",
                "url": "https://diyhistory.org/public/kunshujo/api/elements/95"
            },
            "element_set": {
                "id": 5,
                "name": "IIIF Item Metadata",
                "resource": "element_sets",
                "url": "https://diyhistory.org/public/kunshujo/api/element_sets/5"
            },
            "html": false,
            "text": "https://diyhistory.org/public/kunshujo/oa/items/42957/anno.json"
        },
        {
            "element": {
                "id": 1,
                "name": "Text",
                "resource": "elements",
                "url": "https://diyhistory.org/public/kunshujo/api/elements/1"
            },
            "element_set": {
                "id": 3,
                "name": "Item Type Metadata",
                "resource": "element_sets",
                "url": "https://diyhistory.org/public/kunshujo/api/element_sets/3"
            },
            "html": true,
            "text": "<p>相場仁美、李澈</p>\n<p>[kun070-054-001]</p>"
        },
        {
            "element": {
                "id": 103,
                "name": "Selector",
                "resource": "elements",
                "url": "https://diyhistory.org/public/kunshujo/api/elements/103"
            },
            "element_set": {
                "id": 3,
                "name": "Item Type Metadata",
                "resource": "element_sets",
                "url": "https://diyhistory.org/public/kunshujo/api/element_sets/3"
            },
            "html": false,
            "text": "<svg xmlns='http://www.w3.org/2000/svg'><path xmlns=\"http://www.w3.org/2000/svg\" d=\"M4133.18953,1363.48736h-1103.12455v0h-1103.12455v1809.20397v1809.20397h1103.12455h1103.12455v-1809.20397z\" data-paper-data=\"{&quot;strokeWidth&quot;:1,&quot;rotation&quot;:0,&quot;annotation&quot;:null,&quot;nonHoverStrokeColor&quot;:[&quot;Color&quot;,0,0.74902,1],&quot;editable&quot;:true}\" id=\"rectangle_e842982c-b3ba-421a-a421-558a0387b301\" fill-opacity=\"0.00001\" fill=\"#00bfff\" fill-rule=\"nonzero\" stroke=\"#00bfff\" stroke-width=\"64.00722\" stroke-linecap=\"butt\" stroke-linejoin=\"miter\" stroke-miterlimit=\"10\" stroke-dasharray=\"\" stroke-dashoffset=\"0\" font-family=\"none\" font-weight=\"none\" font-size=\"none\" text-anchor=\"none\" style=\"mix-blend-mode: normal\"/></svg>"
        },
        {
            "element": {
                "id": 104,
                "name": "Annotated Region",
                "resource": "elements",
                "url": "https://diyhistory.org/public/kunshujo/api/elements/104"
            },
            "element_set": {
                "id": 3,
                "name": "Item Type Metadata",
                "resource": "element_sets",
                "url": "https://diyhistory.org/public/kunshujo/api/element_sets/3"
            },
            "html": false,
            "text": "1927,1363,2206,3618"
        },
        {
            "element": {
                "id": 96,
                "name": "JSON Data",
                "resource": "elements",
                "url": "https://diyhistory.org/public/kunshujo/api/elements/96"
            },
            "element_set": {
                "id": 5,
                "name": "IIIF Item Metadata",
                "resource": "element_sets",
                "url": "https://diyhistory.org/public/kunshujo/api/element_sets/5"
            },
            "html": false,
            "text": "{\"@context\":\"http://iiif.io/api/presentation/2/context.json\",\"@type\":\"oa:Annotation\",\"motivation\":[\"oa:commenting\",\"oa:tagging\"],\"resource\":[{\"@type\":\"dctypes:Text\",\"format\":\"text/html\",\"chars\":\"<p>相場仁美、李澈</p>\\n<p>[kun070-054-001]</p>\"},{\"@type\":\"oa:Tag\",\"chars\":\"随意視察旅行案内\"}],\"on\":[{\"@type\":\"oa:SpecificResource\",\"full\":\"https://iiif.dl.itc.u-tokyo.ac.jp/repo/iiif/652cf259-2cc7-462e-8c60-4dfc84e3f2ae/canvas/p54\",\"selector\":{\"@type\":\"oa:Choice\",\"default\":{\"@type\":\"oa:FragmentSelector\",\"value\":\"xywh=1927,1363,2206,3618\"},\"item\":{\"@type\":\"oa:SvgSelector\",\"value\":\"<svg xmlns='http://www.w3.org/2000/svg'><path xmlns=\\\"http://www.w3.org/2000/svg\\\" d=\\\"M4133.18953,1363.48736h-1103.12455v0h-1103.12455v1809.20397v1809.20397h1103.12455h1103.12455v-1809.20397z\\\" data-paper-data=\\\"{&quot;strokeWidth&quot;:1,&quot;rotation&quot;:0,&quot;annotation&quot;:null,&quot;nonHoverStrokeColor&quot;:[&quot;Color&quot;,0,0.74902,1],&quot;editable&quot;:true}\\\" id=\\\"rectangle_e842982c-b3ba-421a-a421-558a0387b301\\\" fill-opacity=\\\"0.00001\\\" fill=\\\"#00bfff\\\" fill-rule=\\\"nonzero\\\" stroke=\\\"#00bfff\\\" stroke-width=\\\"64.00722\\\" stroke-linecap=\\\"butt\\\" stroke-linejoin=\\\"miter\\\" stroke-miterlimit=\\\"10\\\" stroke-dasharray=\\\"\\\" stroke-dashoffset=\\\"0\\\" font-family=\\\"none\\\" font-weight=\\\"none\\\" font-size=\\\"none\\\" text-anchor=\\\"none\\\" style=\\\"mix-blend-mode: normal\\\"/></svg>\"}},\"within\":{\"@id\":\"https://diyhistory.org/public/kunshujo/oa/collections/67/manifest.json\",\"@type\":\"sc:Manifest\"}}],\"@id\":\"https://diyhistory.org/public/kunshujo/oa/items/42957/anno.json\"}"
        },
        {
            "element": {
                "id": 50,
                "name": "Title",
                "resource": "elements",
                "url": "https://diyhistory.org/public/kunshujo/api/elements/50"
            },
            "element_set": {
                "id": 1,
                "name": "Dublin Core",
                "resource": "element_sets",
                "url": "https://diyhistory.org/public/kunshujo/api/element_sets/1"
            },
            "html": true,
            "text": "Annotation: \"相場仁美、李澈\n[kun070-054-001]\""
        }
    ],
    "extended_resources": [],
    "featured": false,
    "files": {
        "count": 0,
        "resource": "files",
        "url": "https://diyhistory.org/public/kunshujo/api/files?item=42957"
    },
    "id": 42957,
    "item_type": {
        "id": 1,
        "name": "Annotation",
        "resource": "item_types",
        "url": "https://diyhistory.org/public/kunshujo/api/item_types/1"
    },
    "modified": "2021-03-11T09:57:47+00:00",
    "owner": {
        "id": 3,
        "resource": "users",
        "url": "https://diyhistory.org/public/kunshujo/api/users/3"
    },
    "public": true,
    "tags": [
        {
            "id": 33741,
            "name": "随意視察旅行案内",
            "resource": "tags",
            "url": "https://diyhistory.org/public/kunshujo/api/tags/33741"
        }
    ],
    "url": "https://diyhistory.org/public/kunshujo/api/items/42957"
}