{
    "added": "2021-02-17T08:20:03+00:00",
    "collection": null,
    "element_texts": [
        {
            "element": {
                "id": 102,
                "name": "On Canvas",
                "resource": "elements",
                "url": "https://diyhistory.org/public/kunshujo/api/elements/102"
            },
            "element_set": {
                "id": 3,
                "name": "Item Type Metadata",
                "resource": "element_sets",
                "url": "https://diyhistory.org/public/kunshujo/api/element_sets/3"
            },
            "html": false,
            "text": "7e907295-9b96-4037-a320-53c0a5343413"
        },
        {
            "element": {
                "id": 105,
                "name": "UUID",
                "resource": "elements",
                "url": "https://diyhistory.org/public/kunshujo/api/elements/105"
            },
            "element_set": {
                "id": 5,
                "name": "IIIF Item Metadata",
                "resource": "element_sets",
                "url": "https://diyhistory.org/public/kunshujo/api/element_sets/5"
            },
            "html": false,
            "text": "cb3fe5ca-bb02-45ac-822f-32bc2e57aff7"
        },
        {
            "element": {
                "id": 95,
                "name": "Original @id",
                "resource": "elements",
                "url": "https://diyhistory.org/public/kunshujo/api/elements/95"
            },
            "element_set": {
                "id": 5,
                "name": "IIIF Item Metadata",
                "resource": "element_sets",
                "url": "https://diyhistory.org/public/kunshujo/api/element_sets/5"
            },
            "html": false,
            "text": "https://diyhistory.org/public/kunshujo/oa/items/49686/anno.json"
        },
        {
            "element": {
                "id": 1,
                "name": "Text",
                "resource": "elements",
                "url": "https://diyhistory.org/public/kunshujo/api/elements/1"
            },
            "element_set": {
                "id": 3,
                "name": "Item Type Metadata",
                "resource": "element_sets",
                "url": "https://diyhistory.org/public/kunshujo/api/element_sets/3"
            },
            "html": true,
            "text": "<p>麻生高代、佘欣怡</p>"
        },
        {
            "element": {
                "id": 103,
                "name": "Selector",
                "resource": "elements",
                "url": "https://diyhistory.org/public/kunshujo/api/elements/103"
            },
            "element_set": {
                "id": 3,
                "name": "Item Type Metadata",
                "resource": "element_sets",
                "url": "https://diyhistory.org/public/kunshujo/api/element_sets/3"
            },
            "html": false,
            "text": "<svg xmlns='http://www.w3.org/2000/svg'><path xmlns=\"http://www.w3.org/2000/svg\" d=\"M1254.6649,3491.65409h1018.88394v0h1018.88394v-780.00312v-780.00312h-1018.88394h-1018.88394v780.00312z\" data-paper-data=\"{&quot;strokeWidth&quot;:1,&quot;rotation&quot;:0,&quot;annotation&quot;:null,&quot;nonHoverStrokeColor&quot;:[&quot;Color&quot;,0,0.74902,1],&quot;editable&quot;:true}\" id=\"rectangle_0ea5b6cf-5982-4c7e-ad61-6a2e4e1869c5\" fill-opacity=\"0.00001\" fill=\"#00bfff\" fill-rule=\"nonzero\" stroke=\"#00bfff\" stroke-width=\"42.60214\" stroke-linecap=\"butt\" stroke-linejoin=\"miter\" stroke-miterlimit=\"10\" stroke-dasharray=\"\" stroke-dashoffset=\"0\" font-family=\"none\" font-weight=\"none\" font-size=\"none\" text-anchor=\"none\" style=\"mix-blend-mode: normal\"/></svg>"
        },
        {
            "element": {
                "id": 104,
                "name": "Annotated Region",
                "resource": "elements",
                "url": "https://diyhistory.org/public/kunshujo/api/elements/104"
            },
            "element_set": {
                "id": 3,
                "name": "Item Type Metadata",
                "resource": "element_sets",
                "url": "https://diyhistory.org/public/kunshujo/api/element_sets/3"
            },
            "html": false,
            "text": "1255,1932,2038,1560"
        },
        {
            "element": {
                "id": 96,
                "name": "JSON Data",
                "resource": "elements",
                "url": "https://diyhistory.org/public/kunshujo/api/elements/96"
            },
            "element_set": {
                "id": 5,
                "name": "IIIF Item Metadata",
                "resource": "element_sets",
                "url": "https://diyhistory.org/public/kunshujo/api/element_sets/5"
            },
            "html": false,
            "text": "{\"@context\":\"http://iiif.io/api/presentation/2/context.json\",\"@type\":\"oa:Annotation\",\"motivation\":[\"oa:commenting\",\"oa:tagging\"],\"resource\":[{\"@type\":\"dctypes:Text\",\"format\":\"text/html\",\"chars\":\"<p>麻生高代、佘欣怡</p>\"},{\"@type\":\"oa:Tag\",\"chars\":\"British_table_salt\"},{\"@type\":\"oa:Tag\",\"chars\":\"Fine_refined\"},{\"@type\":\"oa:Tag\",\"chars\":\"宮崎元□製\"},{\"@type\":\"oa:Tag\",\"chars\":\"衛生\"},{\"@type\":\"oa:Tag\",\"chars\":\"赤穂\"},{\"@type\":\"oa:Tag\",\"chars\":\"食塩\"}],\"on\":[{\"@type\":\"oa:SpecificResource\",\"full\":\"https://iiif.dl.itc.u-tokyo.ac.jp/repo/iiif/92ef19fb-2604-423e-99f6-9b95dec2a17a/canvas/p62\",\"selector\":{\"@type\":\"oa:Choice\",\"default\":{\"@type\":\"oa:FragmentSelector\",\"value\":\"xywh=1255,1932,2038,1560\"},\"item\":{\"@type\":\"oa:SvgSelector\",\"value\":\"<svg xmlns='http://www.w3.org/2000/svg'><path xmlns=\\\"http://www.w3.org/2000/svg\\\" d=\\\"M1254.6649,3491.65409h1018.88394v0h1018.88394v-780.00312v-780.00312h-1018.88394h-1018.88394v780.00312z\\\" data-paper-data=\\\"{&quot;strokeWidth&quot;:1,&quot;rotation&quot;:0,&quot;annotation&quot;:null,&quot;nonHoverStrokeColor&quot;:[&quot;Color&quot;,0,0.74902,1],&quot;editable&quot;:true}\\\" id=\\\"rectangle_0ea5b6cf-5982-4c7e-ad61-6a2e4e1869c5\\\" fill-opacity=\\\"0.00001\\\" fill=\\\"#00bfff\\\" fill-rule=\\\"nonzero\\\" stroke=\\\"#00bfff\\\" stroke-width=\\\"42.60214\\\" stroke-linecap=\\\"butt\\\" stroke-linejoin=\\\"miter\\\" stroke-miterlimit=\\\"10\\\" stroke-dasharray=\\\"\\\" stroke-dashoffset=\\\"0\\\" font-family=\\\"none\\\" font-weight=\\\"none\\\" font-size=\\\"none\\\" text-anchor=\\\"none\\\" style=\\\"mix-blend-mode: normal\\\"/></svg>\"}},\"within\":{\"@id\":\"https://diyhistory.org/public/kunshujo/oa/collections/76/manifest.json\",\"@type\":\"sc:Manifest\"}}],\"@id\":\"https://diyhistory.org/public/kunshujo/oa/items/49686/anno.json\"}"
        },
        {
            "element": {
                "id": 50,
                "name": "Title",
                "resource": "elements",
                "url": "https://diyhistory.org/public/kunshujo/api/elements/50"
            },
            "element_set": {
                "id": 1,
                "name": "Dublin Core",
                "resource": "element_sets",
                "url": "https://diyhistory.org/public/kunshujo/api/element_sets/1"
            },
            "html": true,
            "text": "Annotation: \"麻生高代、佘欣怡\""
        }
    ],
    "extended_resources": [],
    "featured": false,
    "files": {
        "count": 0,
        "resource": "files",
        "url": "https://diyhistory.org/public/kunshujo/api/files?item=49686"
    },
    "id": 49686,
    "item_type": {
        "id": 1,
        "name": "Annotation",
        "resource": "item_types",
        "url": "https://diyhistory.org/public/kunshujo/api/item_types/1"
    },
    "modified": "2021-03-23T23:10:25+00:00",
    "owner": {
        "id": 3,
        "resource": "users",
        "url": "https://diyhistory.org/public/kunshujo/api/users/3"
    },
    "public": true,
    "tags": [
        {
            "id": 50762,
            "name": "british_table_salt",
            "resource": "tags",
            "url": "https://diyhistory.org/public/kunshujo/api/tags/50762"
        },
        {
            "id": 50763,
            "name": "fine_refined",
            "resource": "tags",
            "url": "https://diyhistory.org/public/kunshujo/api/tags/50763"
        },
        {
            "id": 50760,
            "name": "宮崎元□製",
            "resource": "tags",
            "url": "https://diyhistory.org/public/kunshujo/api/tags/50760"
        },
        {
            "id": 8199,
            "name": "衛生",
            "resource": "tags",
            "url": "https://diyhistory.org/public/kunshujo/api/tags/8199"
        },
        {
            "id": 50761,
            "name": "赤穂",
            "resource": "tags",
            "url": "https://diyhistory.org/public/kunshujo/api/tags/50761"
        },
        {
            "id": 11704,
            "name": "食塩",
            "resource": "tags",
            "url": "https://diyhistory.org/public/kunshujo/api/tags/11704"
        }
    ],
    "url": "https://diyhistory.org/public/kunshujo/api/items/49686"
}