{
    "added": "2021-04-09T07:32:39+00:00",
    "collection": null,
    "element_texts": [
        {
            "element": {
                "id": 102,
                "name": "On Canvas",
                "resource": "elements",
                "url": "https://diyhistory.org/public/kunshujo/api/elements/102"
            },
            "element_set": {
                "id": 3,
                "name": "Item Type Metadata",
                "resource": "element_sets",
                "url": "https://diyhistory.org/public/kunshujo/api/element_sets/3"
            },
            "html": false,
            "text": "f26466ac-acdf-4e6e-aaf8-d0606e4d63de"
        },
        {
            "element": {
                "id": 105,
                "name": "UUID",
                "resource": "elements",
                "url": "https://diyhistory.org/public/kunshujo/api/elements/105"
            },
            "element_set": {
                "id": 5,
                "name": "IIIF Item Metadata",
                "resource": "element_sets",
                "url": "https://diyhistory.org/public/kunshujo/api/element_sets/5"
            },
            "html": false,
            "text": "50fc03a7-36fd-48cb-b266-c8a574412317"
        },
        {
            "element": {
                "id": 95,
                "name": "Original @id",
                "resource": "elements",
                "url": "https://diyhistory.org/public/kunshujo/api/elements/95"
            },
            "element_set": {
                "id": 5,
                "name": "IIIF Item Metadata",
                "resource": "element_sets",
                "url": "https://diyhistory.org/public/kunshujo/api/element_sets/5"
            },
            "html": false,
            "text": "https://diyhistory.org/public/kunshujo/oa/items/58787/anno.json"
        },
        {
            "element": {
                "id": 1,
                "name": "Text",
                "resource": "elements",
                "url": "https://diyhistory.org/public/kunshujo/api/elements/1"
            },
            "element_set": {
                "id": 3,
                "name": "Item Type Metadata",
                "resource": "element_sets",
                "url": "https://diyhistory.org/public/kunshujo/api/element_sets/3"
            },
            "html": true,
            "text": "<p>相場仁美</p>"
        },
        {
            "element": {
                "id": 103,
                "name": "Selector",
                "resource": "elements",
                "url": "https://diyhistory.org/public/kunshujo/api/elements/103"
            },
            "element_set": {
                "id": 3,
                "name": "Item Type Metadata",
                "resource": "element_sets",
                "url": "https://diyhistory.org/public/kunshujo/api/element_sets/3"
            },
            "html": false,
            "text": "<svg xmlns='http://www.w3.org/2000/svg'><path xmlns=\"http://www.w3.org/2000/svg\" d=\"M6887.38706,3910.84002h-1397.30588v0h-1397.30588v-749.08461v-749.08461h1397.30588h1397.30588v749.08461z\" data-paper-data=\"{&quot;strokeWidth&quot;:1,&quot;rotation&quot;:0,&quot;annotation&quot;:null,&quot;nonHoverStrokeColor&quot;:[&quot;Color&quot;,0,0.74902,1],&quot;editable&quot;:true}\" id=\"rectangle_ff6ce46b-4027-4e71-bbaa-6a55b4fdcf03\" fill-opacity=\"0.00001\" fill=\"#00bfff\" fill-rule=\"nonzero\" stroke=\"#00bfff\" stroke-width=\"19.84804\" stroke-linecap=\"butt\" stroke-linejoin=\"miter\" stroke-miterlimit=\"10\" stroke-dasharray=\"\" stroke-dashoffset=\"0\" font-family=\"none\" font-weight=\"none\" font-size=\"none\" text-anchor=\"none\" style=\"mix-blend-mode: normal\"/></svg>"
        },
        {
            "element": {
                "id": 104,
                "name": "Annotated Region",
                "resource": "elements",
                "url": "https://diyhistory.org/public/kunshujo/api/elements/104"
            },
            "element_set": {
                "id": 3,
                "name": "Item Type Metadata",
                "resource": "element_sets",
                "url": "https://diyhistory.org/public/kunshujo/api/element_sets/3"
            },
            "html": false,
            "text": "4093,2413,2795,1498"
        },
        {
            "element": {
                "id": 96,
                "name": "JSON Data",
                "resource": "elements",
                "url": "https://diyhistory.org/public/kunshujo/api/elements/96"
            },
            "element_set": {
                "id": 5,
                "name": "IIIF Item Metadata",
                "resource": "element_sets",
                "url": "https://diyhistory.org/public/kunshujo/api/element_sets/5"
            },
            "html": false,
            "text": "{\"@context\":\"http://iiif.io/api/presentation/2/context.json\",\"@type\":\"oa:Annotation\",\"motivation\":[\"oa:commenting\",\"oa:tagging\"],\"resource\":[{\"@type\":\"dctypes:Text\",\"format\":\"text/html\",\"chars\":\"<p>相場仁美</p>\"},{\"@type\":\"oa:Tag\",\"chars\":\"御饅頭調進所\"},{\"@type\":\"oa:Tag\",\"chars\":\"本郷三丁目\"},{\"@type\":\"oa:Tag\",\"chars\":\"栄泉堂岡埜\"}],\"on\":[{\"@type\":\"oa:SpecificResource\",\"full\":\"https://iiif.dl.itc.u-tokyo.ac.jp/repo/iiif/fe60f253-679a-4b1f-bf92-203bd1c2498a/canvas/p188\",\"selector\":{\"@type\":\"oa:Choice\",\"default\":{\"@type\":\"oa:FragmentSelector\",\"value\":\"xywh=4093,2413,2795,1498\"},\"item\":{\"@type\":\"oa:SvgSelector\",\"value\":\"<svg xmlns='http://www.w3.org/2000/svg'><path xmlns=\\\"http://www.w3.org/2000/svg\\\" d=\\\"M6887.38706,3910.84002h-1397.30588v0h-1397.30588v-749.08461v-749.08461h1397.30588h1397.30588v749.08461z\\\" data-paper-data=\\\"{&quot;strokeWidth&quot;:1,&quot;rotation&quot;:0,&quot;annotation&quot;:null,&quot;nonHoverStrokeColor&quot;:[&quot;Color&quot;,0,0.74902,1],&quot;editable&quot;:true}\\\" id=\\\"rectangle_ff6ce46b-4027-4e71-bbaa-6a55b4fdcf03\\\" fill-opacity=\\\"0.00001\\\" fill=\\\"#00bfff\\\" fill-rule=\\\"nonzero\\\" stroke=\\\"#00bfff\\\" stroke-width=\\\"19.84804\\\" stroke-linecap=\\\"butt\\\" stroke-linejoin=\\\"miter\\\" stroke-miterlimit=\\\"10\\\" stroke-dasharray=\\\"\\\" stroke-dashoffset=\\\"0\\\" font-family=\\\"none\\\" font-weight=\\\"none\\\" font-size=\\\"none\\\" text-anchor=\\\"none\\\" style=\\\"mix-blend-mode: normal\\\"/></svg>\"}},\"within\":{\"@id\":\"https://diyhistory.org/public/kunshujo/oa/collections/73/manifest.json\",\"@type\":\"sc:Manifest\"}}],\"@id\":\"https://diyhistory.org/public/kunshujo/oa/items/58787/anno.json\"}"
        },
        {
            "element": {
                "id": 50,
                "name": "Title",
                "resource": "elements",
                "url": "https://diyhistory.org/public/kunshujo/api/elements/50"
            },
            "element_set": {
                "id": 1,
                "name": "Dublin Core",
                "resource": "element_sets",
                "url": "https://diyhistory.org/public/kunshujo/api/element_sets/1"
            },
            "html": true,
            "text": "Annotation: \"相場仁美\""
        }
    ],
    "extended_resources": [],
    "featured": false,
    "files": {
        "count": 0,
        "resource": "files",
        "url": "https://diyhistory.org/public/kunshujo/api/files?item=58787"
    },
    "id": 58787,
    "item_type": {
        "id": 1,
        "name": "Annotation",
        "resource": "item_types",
        "url": "https://diyhistory.org/public/kunshujo/api/item_types/1"
    },
    "modified": "2021-04-09T07:33:50+00:00",
    "owner": {
        "id": 3,
        "resource": "users",
        "url": "https://diyhistory.org/public/kunshujo/api/users/3"
    },
    "public": true,
    "tags": [
        {
            "id": 51786,
            "name": "御饅頭調進所",
            "resource": "tags",
            "url": "https://diyhistory.org/public/kunshujo/api/tags/51786"
        },
        {
            "id": 2181,
            "name": "本郷三丁目",
            "resource": "tags",
            "url": "https://diyhistory.org/public/kunshujo/api/tags/2181"
        },
        {
            "id": 9217,
            "name": "栄泉堂岡埜",
            "resource": "tags",
            "url": "https://diyhistory.org/public/kunshujo/api/tags/9217"
        }
    ],
    "url": "https://diyhistory.org/public/kunshujo/api/items/58787"
}